icefarm/__init__.py
icefarm-0.1.1.dist-info/METADATA
icefarm-0.1.1.dist-info/WHEEL
icefarm-0.1.1.dist-info/top_level.txt
icefarm-0.1.1.dist-info/RECORD
