Metadata-Version: 2.4
Name: icefarm
Version: 0.1.1
Requires-Dist: Flask
Requires-Dist: flask-socketio
Requires-Dist: websocket-client
Requires-Dist: uvicorn
Requires-Dist: pexpect
Requires-Dist: psycopg[binary]
Requires-Dist: pyudev
Requires-Dist: requests
Requires-Dist: schedule
Requires-Dist: pyserial
Requires-Dist: python-dotenv
Requires-Dist: asgiref
Requires-Dist: pytest
